localized_recurrence/__init__.py
localized_recurrence/admin.py
localized_recurrence/apps.py
localized_recurrence/fields.py
localized_recurrence/models.py
localized_recurrence/version.py
localized_recurrence/migrations/0001_initial.py
localized_recurrence/migrations/0002_localizedrecurrence_offset2.py
localized_recurrence/migrations/0003_offset_data_migration.py
localized_recurrence/migrations/0004_auto_20161108_2151.py
localized_recurrence/migrations/__init__.py
localized_recurrence/tests/__init__.py
localized_recurrence/tests/admin_tests.py
localized_recurrence/tests/fields_tests.py
localized_recurrence/tests/models_tests.py
django_localized_recurrence-4.1.1.dist-info/LICENSE
django_localized_recurrence-4.1.1.dist-info/METADATA
django_localized_recurrence-4.1.1.dist-info/WHEEL
django_localized_recurrence-4.1.1.dist-info/top_level.txt
django_localized_recurrence-4.1.1.dist-info/RECORD
