Metadata-Version: 2.1
Name: django-localized-recurrence
Version: 4.1.1
Summary: Store events that recur in users' local times.
Author: Erik Swanson
Author-email: theerikswanson@gmail.com
License: MIT License
Classifier: Environment :: Web Environment
Classifier: Framework :: Django
Classifier: Framework :: Django :: 3.2
Classifier: Framework :: Django :: 4.0
Classifier: Framework :: Django :: 4.1
Classifier: Framework :: Django :: 4.2
Classifier: Intended Audience :: Developers
Classifier: License :: OSI Approved :: MIT License
Classifier: Operating System :: OS Independent
Classifier: Programming Language :: Python
Classifier: Programming Language :: Python :: 3.7
Classifier: Programming Language :: Python :: 3.8
Classifier: Programming Language :: Python :: 3.9
Classifier: Topic :: Internet :: WWW/HTTP
Classifier: Topic :: Internet :: WWW/HTTP :: Dynamic Content
License-File: LICENSE
Requires-Dist: Django (>=3.2)
Requires-Dist: ambition-utils (>=3.1.1)
Requires-Dist: fleming (>=0.6.0)
Requires-Dist: python-dateutil
Requires-Dist: pytz
